<?xml version="1.0" encoding="UTF-8"?>
<?xml-stylesheet type="text/css" href="eac.css"?>
<eac-cpf xmlns="urn:isbn:1-931666-33-4" xmlns:xsi="http://www.w3.org/2001/XMLSchema-instance"
    xsi:schemaLocation="urn:isbn:1-931666-33-4 http://eac.staatsbibliothek-berlin.de/schema/cpf.xsd">
    <control><recordId>GB-237-eac-p4236</recordId><maintenanceStatus>new</maintenanceStatus>
        <publicationStatus>inProcess</publicationStatus>
        <maintenanceAgency>
            <agencyCode>GB-237</agencyCode>
            <agencyName>Special Collections, Edinburgh University Library</agencyName>
        </maintenanceAgency><languageDeclaration>
            <language languageCode="eng">English</language>
            <script scriptCode="Latn" xml:lang="Gla">Gaelic</script>
        </languageDeclaration><conventionDeclaration>
            <abbreviation>ISAAR(CPF)</abbreviation>
            <citation xmlns:ns1="http://www.w3.org/1999/xlink" ns1:type="simple">
                <span localType="bibTitle">International Standard Archival Authority Record For
                    Corporate Bodies, Persons and Families</span>
            </citation>
        </conventionDeclaration><maintenanceHistory>
            <maintenanceEvent>
                <eventType>created</eventType>
                <eventDateTime standardDateTime="2010-06-29">29 June 2010</eventDateTime>
                <agentType>human</agentType>
                <agent>Scott Broderick</agent>
                <eventDescription>draft completed</eventDescription>
            </maintenanceEvent>
            <maintenanceEvent>
                <eventType>created</eventType>
                <eventDateTime standardDateTime="2012-10-26">26 October 2012</eventDateTime>
                <agentType>human</agentType>
                <agent>Lynne Bulmer</agent>
                <eventDescription>draft revised</eventDescription>
            </maintenanceEvent>
            <maintenanceEvent>
                <eventType>revised</eventType>
                <eventDateTime>14 January 2013</eventDateTime>
                <agentType>human</agentType>
                <agent>Guinevere Barlow</agent>
            </maintenanceEvent>
        </maintenanceHistory><sources>
            <source xmlns:ns1="http://www.w3.org/1999/xlink" ns1:type="simple">
                <sourceEntry>1841 census for South Uist</sourceEntry>
                <descriptiveNote>
                    <p><span localType="ead-unitid">Census 1841 118/00 011/00 001</span>
                        <span localType="ead-repository">General Register Office for
                        Scotland</span></p>
                </descriptiveNote>
            </source>
            <source xmlns:ns1="http://www.w3.org/1999/xlink" ns1:type="simple">
                <sourceEntry>1851 census for South Uist</sourceEntry>
                <descriptiveNote>
                    <p><span localType="ead-unitid">Census 1851 118/00 023/00 018</span>
                        <span localType="ead-repository">General Register Office for
                        Scotland</span></p>
                </descriptiveNote>
            </source>
            <source xmlns:ns1="http://www.w3.org/1999/xlink" ns1:type="simple">
                <sourceEntry>1861 census for South Uist</sourceEntry>
                <descriptiveNote>
                    <p><span localType="ead-unitid">Census 1861 118/02 004/02 001</span>
                        <span localType="ead-repository">General Register Office for
                        Scotland</span></p>
                </descriptiveNote>
            </source>
            <source xmlns:ns1="http://www.w3.org/1999/xlink" ns1:type="simple">
                <sourceEntry>1871 census for South Uist</sourceEntry>
                <descriptiveNote>
                    <p><span localType="ead-unitid">Census 1871 118/02 004/02 007</span>
                        <span localType="ead-repository">General Register Office for
                        Scotland</span></p>
                </descriptiveNote>
            </source>
            <source>
                <sourceEntry>Death certificate</sourceEntry>
                <descriptiveNote>
                    <p><span localType="ead-unitid">Death 1880 118/02 0004</span>
                        <span localType="ead-repository" xmlns:ns1="http://www.w3.org/1999/xlink"
                            >General Register Office for Scotland</span></p>
                </descriptiveNote>
            </source>
            <source>
                <sourceEntry>Transcription notebook of Alexander Carmichael</sourceEntry>
                <descriptiveNote>
                    <p><span localType="ead-unitid">GB 237 Coll-97/CW87/20</span><span
                            localType="ead-repository">Edinburgh University Library</span></p>
                </descriptiveNote>
            </source>
            <source>
                <sourceEntry>Transcription notebook of Alexander Carmichael</sourceEntry>
                <descriptiveNote>
                    <p><span localType="ead-unitid">GB 237 Coll-97/CW87/21</span><span
                            localType="ead-repository">Edinburgh University Library</span></p>
                </descriptiveNote>
            </source>
            <source>
                <sourceEntry>Field notebook of Alexander Carmichael</sourceEntry>
                <descriptiveNote>
                    <p><span localType="ead-unitid">GB 237 Coll-97/CW90/36</span><span
                            localType="ead-repository">Edinburgh University Library</span></p>
                </descriptiveNote>
            </source>
            <source>
                <sourceEntry>Field notebook of Alexander Carmichael</sourceEntry>
                <descriptiveNote>
                    <p><span localType="ead-unitid">GB 237 Coll-97/CW90/37</span><span
                            localType="ead-repository">Edinburgh University Library</span></p>
                </descriptiveNote>
            </source>
            <source>
                <sourceEntry>Notebook of Alexander Carmichael</sourceEntry>
                <descriptiveNote>
                    <p><span localType="ead-unitid">GB 237 Coll-97/CW126g/39</span><span
                            localType="ead-repository">Edinburgh University Library</span></p>
                </descriptiveNote>
            </source>
        </sources></control>
    <cpfDescription>
        <identity>
            <entityId>GB-237-EAC-p4236</entityId>
            <entityType>person</entityType>
            <nameEntry>
                <part localType="family">MacPhie</part>
                <part localType="given">Barbara</part>
            </nameEntry>
            <descriptiveNote>
                <p>Pauper, Drimsdale, South Uist</p>
            </descriptiveNote></identity>
        <description>
            <existDates><dateRange><fromDate standardDate="1800" notBefore="1795" notAfter="1805"
                        >c1800</fromDate><toDate standardDate="1880-01-18">18 January
                    1880</toDate></dateRange></existDates>
            <biogHist>
                <p>Barbara MacPhie [MacPhee] was born to Dugald MacPhee, farmer, and Janet MacPhee
                    née Macdonald. She is listed in the 1841 census for South Uist along with Donald
                    MacDonald (12). In the 1851 census, she is listed as head of the household along
                    with Donald MacPhee (48) a farmer (most likely her brother). By the time of the
                    1861 census, she appears to be living alone and is listed as a pauper in North
                    Uist; this could be an error on the census as South Uist is more likely. In
                    1871, she is recorded as being aged 73, a pauper living with her brother Donald
                    MacPhee in South Uist. </p>
                <p>Barbara died of chronic asthma, unmarried and aged around 80 with her nephew John
                    MacPhee present. </p>
                <chronList>
                    <chronItem>
                        <date standardDate="1800" notAfter="1805" notBefore="1795">c1800</date>
                        <placeEntry>South Uist</placeEntry>
                        <event>birth</event>
                    </chronItem>
                    <chronItem>
                        <date standardDate="1872-03-27">27 March
                            1872</date>
                        <placeEntry>Drimsdale, South Uist</placeEntry>
                        <event>met with Alexander Carmichael</event>
                    </chronItem>
                    <chronItem>
                        <date standardDate="1883">1883</date>
                        <placeEntry>Drimsdale, South Uist</placeEntry>
                        <event>met with Alexander Carmichael</event>
                    </chronItem>
                    <chronItem>
                        <date standardDate="1893" notAfter="1898" notBefore="1888">c1893</date>
                        <placeEntry>South Uist</placeEntry>
                        <event>mentioned in the notebook</event>
                    </chronItem>
                    <chronItem><date standardDate="1880-01-18">18 January
                            1880</date><placeEntry>Drimore, South
                            Uist</placeEntry><event>death</event></chronItem>
                </chronList>
            </biogHist>
        </description>
    </cpfDescription>
</eac-cpf>
